kili-common-storage/__init__.py
kili-common-storage/constants.py
kili-common-storage/decorator.py
kili-common-storage/exceptions.py
kili-common-storage/loggings.py
kili-common-storage/object_storage.py
kili_common_storage/__init__.py
kili_common_storage/constants.py
kili_common_storage/decorator.py
kili_common_storage/exceptions.py
kili_common_storage/loggings.py
kili_common_storage/object_storage.py
kili_common_storage-0.0.24.post2.dist-info/METADATA
kili_common_storage-0.0.24.post2.dist-info/WHEEL
kili_common_storage-0.0.24.post2.dist-info/top_level.txt
kili_common_storage-0.0.24.post2.dist-info/RECORD
